portainer_api/__init__.py
portainer_api/api_client.py
portainer_api/configuration.py
portainer_api/rest.py
portainer_api/api/__init__.py
portainer_api/api/auth_api.py
portainer_api/api/dockerhub_api.py
portainer_api/api/endpoint_groups_api.py
portainer_api/api/endpoints_api.py
portainer_api/api/extensions_api.py
portainer_api/api/registries_api.py
portainer_api/api/resource_controls_api.py
portainer_api/api/roles_api.py
portainer_api/api/settings_api.py
portainer_api/api/stacks_api.py
portainer_api/api/status_api.py
portainer_api/api/tags_api.py
portainer_api/api/team_memberships_api.py
portainer_api/api/teams_api.py
portainer_api/api/templates_api.py
portainer_api/api/upload_api.py
portainer_api/api/users_api.py
portainer_api/models/__init__.py
portainer_api/models/access_policy.py
portainer_api/models/authenticate_user_request.py
portainer_api/models/authenticate_user_response.py
portainer_api/models/authorizations.py
portainer_api/models/azure_credentials.py
portainer_api/models/docker_hub.py
portainer_api/models/docker_hub_subset.py
portainer_api/models/docker_hub_update_request.py
portainer_api/models/endpoint.py
portainer_api/models/endpoint_group.py
portainer_api/models/endpoint_group_create_request.py
portainer_api/models/endpoint_group_list_response.py
portainer_api/models/endpoint_group_update_request.py
portainer_api/models/endpoint_job_request.py
portainer_api/models/endpoint_list_response.py
portainer_api/models/endpoint_subset.py
portainer_api/models/endpoint_update_request.py
portainer_api/models/extension.py
portainer_api/models/extension_create_request.py
portainer_api/models/extension_list_response.py
portainer_api/models/extension_update_request.py
portainer_api/models/generic_error.py
portainer_api/models/ldap_group_search_settings.py
portainer_api/models/ldap_search_settings.py
portainer_api/models/ldap_settings.py
portainer_api/models/license_information.py
portainer_api/models/pair.py
portainer_api/models/public_settings_inspect_response.py
portainer_api-1.22.1.1.dist-info/METADATA
portainer_api-1.22.1.1.dist-info/WHEEL
portainer_api-1.22.1.1.dist-info/top_level.txt
portainer_api-1.22.1.1.dist-info/RECORD
