Metadata-Version: 1.0
Name: portainer-api
Version: 1.22.1.1
Summary: Portainer API
Home-page: UNKNOWN
Author: UNKNOWN
Author-email: info@portainer.io
License: UNKNOWN
Keywords: Swagger,Portainer API
Platform: UNKNOWN
